{"_path":"/modal/odontologia-especilizada-en-quito","_dir":"modal","_draft":false,"_partial":false,"_locale":"en","contenido":"Somos KEVA Dental Concept <h1>clínica dental en Quito Ecuador</h1>: reconocida como spa dental, donde nos especializamos en <h2>diseño de sonrisas</h2> también <h2>implantes dentales</h2> y además <h2>ortodoncia</h2>. Nuestro grupo de <h4>odontólogos</h4> también están altamente calificados en: <h3>Rehabilitación oral</h3> <h3>Estética dental</h3> <h3>Blanqueamiento dental</h3> <h3>Bracket estéticos</h3> <h3>Retenedores de dientes</h3> <h3>Ortodoncia invisible</h3> <h3>Brackets de zafiro</h3> Tu <h5>tratamiento dental</h5> esta en las mejores manos, personaliza tu sonrisa de acuerdo a la anatomía de tu rostro","_id":"content:modal:odontologia-especilizada-en-quito.json","_type":"json","title":"Odontologia Especilizada En Quito","_source":"content","_file":"modal/odontologia-especilizada-en-quito.json","_extension":"json"}